waspy/__init__.py
waspy/_cors.py
waspy/app.py
waspy/client.py
waspy/configuration.py
waspy/ctx.py
waspy/errorlogging.py
waspy/exceptions.py
waspy/listeners/__init__.py
waspy/listeners/rabbitmq_listener.py
waspy/listeners/transport_listener_abc.py
waspy/parser.py
waspy/router.py
waspy/transports/__init__.py
waspy/transports/httptransport.py
waspy/transports/rabbit_patches.py
waspy/transports/rabbitmqtransport.py
waspy/transports/testtransport.py
waspy/transports/transportabc.py
waspy/webtypes.py
waspy/worker.py
waspy-0.45.5.dist-info/LICENSE
waspy-0.45.5.dist-info/WHEEL
waspy-0.45.5.dist-info/METADATA
waspy-0.45.5.dist-info/RECORD
