Metadata-Version: 2.1
Name: waspy
Version: 0.45.5
Summary: Async Microservices Framework
Home-page: https://github.com/wasp/waspy
License: Apache-2.0
Keywords: wasp,async,asyncio,rest framework,rabbitmq,microservices
Author: Nick Humrich
Author-email: nhumrich@canopytax.com
Requires-Python: >=3.7,<4.0
Classifier: Development Status :: 3 - Alpha
Classifier: Intended Audience :: Developers
Classifier: License :: OSI Approved :: Apache Software License
Classifier: Natural Language :: English
Classifier: Operating System :: POSIX
Classifier: Programming Language :: Python :: 3
Classifier: Programming Language :: Python :: 3.7
Requires-Dist: PyYAML
Requires-Dist: aenum (==1.4.5)
Requires-Dist: aioamqp
Requires-Dist: httptools
Project-URL: Repository, https://github.com/wasp/waspy
